{
    "projectId": "64eb1f41c5f0f30ab422",
    "projectName": "Auth app with Appwrite",
    "functions": [
        {
            "$id": "64f19915b6569c25db49",
            "name": "addUserToTeamA",
            "runtime": "node-16.0",
            "path": "functions/addUserToTeamA",
            "entrypoint": "src/index.js",
            "ignore": [
                "node_modules",
                ".npm"
            ],
            "execute": [
                "any"
            ],
            "events": [],
            "schedule": "",
            "timeout": 15
        },
        {
            "$id": "64f1f242a42408a603f1",
            "name": "Test Function",
            "runtime": "node-16.0",
            "path": "functions/Test Function",
            "entrypoint": "src/index.js",
            "ignore": [
                "node_modules",
                ".npm"
            ],
            "execute": ["any"],
            "events": [],
            "schedule": "",
            "timeout": 15
        }
    ]
}